mlperf/__init__.py
mlperf/agents/__init__.py
mlperf/agents/base.py
mlperf/agents/benchmark.py
mlperf/agents/optimization.py
mlperf/agents/performance.py
mlperf/agents/swarm_manager.py
mlperf/api/__init__.py
mlperf/api/main.py
mlperf/auth/__init__.py
mlperf/auth/api.py
mlperf/auth/jwt.py
mlperf/auth/models.py
mlperf/auth/rate_limit.py
mlperf/auth/schemas.py
mlperf/auth/security.py
mlperf/cli/__init__.py
mlperf/cli/main.py
mlperf/cli/shell_gpt_cli.py
mlperf/hardware/__init__.py
mlperf/hardware/cpu.py
mlperf/hardware/gpu.py
mlperf/hardware/memory.py
mlperf/models/__init__.py
mlperf/models/benchmark.py
mlperf/models/experiment.py
mlperf/models/hardware.py
mlperf/models/optimization.py
mlperf/models/project.py
mlperf/optimization/__init__.py
mlperf/optimization/distributed.py
mlperf/utils/__init__.py
mlperf/utils/cache.py
mlperf/utils/config.py
mlperf/utils/database.py
mlperf/utils/logging.py
mlperf/workers/__init__.py
mlperf/workers/main.py
openperformance-1.0.1.dist-info/licenses/LICENSE
openperformance-1.0.1.dist-info/METADATA
openperformance-1.0.1.dist-info/WHEEL
openperformance-1.0.1.dist-info/entry_points.txt
openperformance-1.0.1.dist-info/top_level.txt
openperformance-1.0.1.dist-info/RECORD
