Metadata-Version: 2.4
Name: openperformance
Version: 1.0.1
Summary: Enterprise-grade ML Performance Engineering Platform for optimization, monitoring, and deployment
Home-page: https://github.com/llamasearchai/OpenPerformance
Author: Nik Jois
Author-email: OpenPerformance Team <team@openperformance.ai>
Maintainer-email: OpenPerformance Maintainers <maintainers@openperformance.ai>
License: MIT
Project-URL: Homepage, https://github.com/openperformance/openperformance
Project-URL: Documentation, https://openperformance.io
Project-URL: Repository, https://github.com/openperformance/openperformance.git
Project-URL: Bug Tracker, https://github.com/openperformance/openperformance/issues
Project-URL: Changelog, https://github.com/openperformance/openperformance/blob/main/CHANGELOG.md
Keywords: ml,performance,optimization,monitoring,deployment,mlops,ai
Classifier: Development Status :: 4 - Beta
Classifier: Intended Audience :: Developers
Classifier: Intended Audience :: Science/Research
Classifier: License :: OSI Approved :: MIT License
Classifier: Operating System :: OS Independent
Classifier: Programming Language :: Python :: 3
Classifier: Programming Language :: Python :: 3.9
Classifier: Programming Language :: Python :: 3.10
Classifier: Programming Language :: Python :: 3.11
Classifier: Programming Language :: Python :: 3.12
Classifier: Topic :: Scientific/Engineering :: Artificial Intelligence
Classifier: Topic :: Software Development :: Libraries :: Python Modules
Requires-Python: >=3.9
License-File: LICENSE
Requires-Dist: fastapi>=0.104.0
Requires-Dist: uvicorn[standard]>=0.24.0
Requires-Dist: pydantic>=2.5.0
Requires-Dist: pydantic-settings>=2.1.0
Requires-Dist: typer[all]>=0.9.0
Requires-Dist: numpy>=1.24.0
Requires-Dist: torch>=2.1.0
Requires-Dist: sqlalchemy>=2.0.0
Requires-Dist: redis>=5.0.0
Requires-Dist: psutil>=5.9.0
Requires-Dist: openai>=1.20.0
Requires-Dist: httpx>=0.25.0
Requires-Dist: python-jose[cryptography]>=3.3.0
Requires-Dist: passlib[bcrypt]>=1.7.4
Requires-Dist: python-multipart>=0.0.6
Provides-Extra: dev
Requires-Dist: pytest>=7.4.0; extra == "dev"
Requires-Dist: black>=23.11.0; extra == "dev"
Requires-Dist: ruff>=0.1.0; extra == "dev"
Requires-Dist: mypy>=1.7.0; extra == "dev"
Provides-Extra: docs
Requires-Dist: mkdocs>=1.5.0; extra == "docs"
Requires-Dist: mkdocs-material>=9.4.0; extra == "docs"
Requires-Dist: sphinx>=7.2.0; extra == "docs"
Provides-Extra: enterprise
Requires-Dist: enterprise-logging>=1.0.0; extra == "enterprise"
Requires-Dist: enterprise-security>=2.0.0; extra == "enterprise"
Requires-Dist: enterprise-monitoring>=1.5.0; extra == "enterprise"
Dynamic: author
Dynamic: home-page
Dynamic: license-file
Dynamic: requires-python
